{"vaults":{"b27a41893de5d8c7":{"path":"C:\\Users\\jimmy\\Dev\\obsidian\\KaaS","ts":1635903215374,"open":true},"138da596dac59cd3":{"path":"C:\\Users\\jimmy\\Dev\\obsidian\\KaaS - Copy","ts":1635887231996},"aa8daa113150fd6d":{"path":"C:\\Users\\jimmy\\Dev\\obsidian\\KaaS-ReDo","ts":1635887243517},"5ff0a3acced363e2":{"path":"C:\\Users\\jimmy\\Downloads\\obsidian-hub-0.2.0","ts":1635890210380},"23a70cee93b3dd06":{"path":"C:\\Users\\jimmy\\Downloads\\obsidian-hub-0.2.0\\obsidian-hub-0.2.0","ts":1635890222653},"db5c38a0e46a2307":{"path":"C:\\Users\\jimmy\\Dev\\obsidian\\KaaS-2","ts":1635903857258,"open":true}},"openSchemes":{"app":true}}